django_ipc/__init__.py
django_ipc/bridge/__init__.py
django_ipc/bridge/bridge.py
django_ipc/codegen/__init__.py
django_ipc/codegen/__main__.py
django_ipc/codegen/cli.py
django_ipc/codegen/discovery.py
django_ipc/codegen/poc_test.py
django_ipc/codegen/generators/__init__.py
django_ipc/codegen/generators/go_websocket/__init__.py
django_ipc/codegen/generators/go_websocket/generator.py
django_ipc/codegen/generators/go_websocket/templates/.gitignore.j2
django_ipc/codegen/generators/go_websocket/templates/Makefile.j2
django_ipc/codegen/generators/go_websocket/templates/README.md.j2
django_ipc/codegen/generators/go_websocket/templates/client.go.j2
django_ipc/codegen/generators/go_websocket/templates/go.mod.j2
django_ipc/codegen/generators/go_websocket/templates/type_file.go.j2
django_ipc/codegen/generators/go_websocket/templates/types.go.j2
django_ipc/codegen/generators/python_websocket/__init__.py
django_ipc/codegen/generators/python_websocket/generator.py
django_ipc/codegen/generators/python_websocket/templates/.editorconfig.j2
django_ipc/codegen/generators/python_websocket/templates/.gitignore.j2
django_ipc/codegen/generators/python_websocket/templates/README.md.j2
django_ipc/codegen/generators/python_websocket/templates/__init__.py.j2
django_ipc/codegen/generators/python_websocket/templates/client.py.j2
django_ipc/codegen/generators/python_websocket/templates/models.py.j2
django_ipc/codegen/generators/python_websocket/templates/pyproject.toml.j2
django_ipc/codegen/generators/python_websocket/templates/requirements.txt.j2
django_ipc/codegen/generators/python_websocket/templates/setup.py.j2
django_ipc/codegen/generators/typescript_websocket/__init__.py
django_ipc/codegen/generators/typescript_websocket/generator.py
django_ipc/codegen/generators/typescript_websocket/templates/.editorconfig.j2
django_ipc/codegen/generators/typescript_websocket/templates/.eslintrc.json.j2
django_ipc/codegen/generators/typescript_websocket/templates/.gitignore.j2
django_ipc-1.0.9.dist-info/METADATA
django_ipc-1.0.9.dist-info/WHEEL
django_ipc-1.0.9.dist-info/RECORD
