Metadata-Version: 2.4
Name: django-ipc
Version: 1.0.9
Summary: 🚀 Production-ready WebSocket RPC for Django - Auto-generated clients, 100% type-safe, 5-minute setup
Project-URL: Homepage, https://djangocfg.com
Project-URL: Documentation, https://djangocfg.com/docs/features/integrations/websocket-ipc
Project-URL: Quick Start, https://djangocfg.com/docs/features/integrations/websocket-ipc/quick-start
Project-URL: Live Demo, http://demo.djangocfg.com
Project-URL: Repository, https://github.com/markolofsen/django-ipc
Project-URL: Issues, https://github.com/markolofsen/django-ipc/issues
Project-URL: Django-CFG Framework, https://github.com/markolofsen/django-cfg
Author-email: Django-CFG Team <info@djangocfg.com>
Maintainer-email: Django-CFG Team <info@djangocfg.com>
License: MIT
Keywords: auto-generated-clients,django,django-channels-alternative,django-ipc,django-notifications,django-real-time,django-websocket,ipc,pydantic,real-time,redis,type-safety,websocket,websocket-rpc,websocket-server
Classifier: Development Status :: 4 - Beta
Classifier: Framework :: Django
Classifier: Intended Audience :: Developers
Classifier: License :: OSI Approved :: MIT License
Classifier: Operating System :: OS Independent
Classifier: Programming Language :: Python
Classifier: Programming Language :: Python :: 3
Classifier: Programming Language :: Python :: 3.10
Classifier: Programming Language :: Python :: 3.11
Classifier: Programming Language :: Python :: 3.12
Classifier: Programming Language :: Python :: 3.13
Classifier: Topic :: Internet :: WWW/HTTP
Classifier: Topic :: Software Development :: Libraries :: Python Modules
Classifier: Topic :: System :: Distributed Computing
Classifier: Typing :: Typed
Requires-Python: <4.0,>=3.10
Requires-Dist: aiohttp<4.0,>=3.11.0
Requires-Dist: hiredis<4.0,>=2.0.0
Requires-Dist: jinja2<4.0,>=3.1.0
Requires-Dist: loguru<1.0,>=0.7.0
Requires-Dist: packaging>=24.0
Requires-Dist: pydantic<3.0,>=2.11.0
Requires-Dist: pyjwt<3.0,>=2.10.0
Requires-Dist: redis<7.0,>=6.4.0
Requires-Dist: rich<15.0,>=14.1.0
Requires-Dist: websockets<16.0,>=15.0
Provides-Extra: dev
Requires-Dist: black<26.0,>=25.9; extra == 'dev'
Requires-Dist: build<2.0,>=1.3; extra == 'dev'
Requires-Dist: isort<7.0,>=6.0; extra == 'dev'
Requires-Dist: mypy<2.0,>=1.18; extra == 'dev'
Requires-Dist: pytest-asyncio<1.0,>=0.25; extra == 'dev'
Requires-Dist: pytest-cov<8.0,>=7.0; extra == 'dev'
Requires-Dist: pytest-mock<4.0,>=3.15; extra == 'dev'
Requires-Dist: pytest<9.0,>=8.4; extra == 'dev'
Requires-Dist: twine<7.0,>=6.2; extra == 'dev'
Provides-Extra: test
Requires-Dist: pytest-asyncio<1.0,>=0.25; extra == 'test'
Requires-Dist: pytest-cov<8.0,>=7.0; extra == 'test'
Requires-Dist: pytest-mock<4.0,>=3.15; extra == 'test'
Requires-Dist: pytest<9.0,>=8.4; extra == 'test'
